<titlePackXML projectenviro="Storm">
	<global>
		<News color=""/>
		<Logo path="file://Media\Images\Logos\Logos.png" />
		<Background path="" />
		<BackgroundImage path="file://Media\Images\Logos\PackImage.webm" />
		<Music path="file://Media\Musics\Storm\Race\!Night\DAY_01_Track_03.ogg" />
		<Style MainTitlePolice="TextTitle3" SectionsPolice="TextRaceMessageBig" />
	</global>

	<Multiplayer logo="file://Media/MEDIABROWSER_HiddenResources/Common/Images/Menus/Buttons/Logo_Online.dds" activated="True" color="eff" allowallmodes="True" displaytitleserversonly="True">
			<asset id="Online_UGCAsset-0" isdefault="no" titlename="Modes\ShootMania\Obstacle.Script.txt"/>
	<asset id="Online_UGCAsset-1" isdefault="no" titlename="Modes\ShootMania\Sprint.Script.txt"/>

	</Multiplayer>
	<LocalPlay logo="file://Media/MEDIABROWSER_HiddenResources/Common/Images/Menus/Buttons/Logo_LocalPlay.dds" activated="True" color="efe">
			<asset id="LocalNetwork" isdefault="yes" titlename="Local Network" isvisibleinmaker="True"/>
	<asset id="LocalPlay_UGCAsset-0" isdefault="no" titlename="Modes\ShootMania\Obstacle.Script.txt"/>
	<asset id="LocalPlay_UGCAsset-1" isdefault="no" titlename="Modes\ShootMania\Sprint.Script.txt"/>

	</LocalPlay>
	<Editors logo="file://Media/MEDIABROWSER_HiddenResources/Common/Images/Menus/Buttons/Logo_Editor.dds" activated="True" color="fed" mapeditor="">
	<asset id="NewMap" isdefault="yes" titlename=""/>
	<asset id="EditReplay" isdefault="yes" titlename=""/>
	<asset id="TitleTools" isdefault="yes" titlename=""/>

	</Editors>
<Resources flashurl="obstacle@smokegun"/>
	<Ingame accelcoef="0.1" controlcoef="0.1" gravitycoef="0.1">
	</Ingame>
	<Profile>
		<param id="0" MonParam="aaa" />
	</Profile>
</titlePackXML>